barney_log/__init__.py
barney_log/barney_log.py
barney_log-0.1.dist-info/METADATA
barney_log-0.1.dist-info/WHEEL
barney_log-0.1.dist-info/top_level.txt
barney_log-0.1.dist-info/RECORD
